<?xml version="1.0" encoding="utf-8" ?>
<dwsync>
<file name="icons.png" server="unas.com.tw/www/test/kiang/" local="129829037600634772" remote="129829047000000000" />
<file name="line1.png" server="unas.com.tw/www/test/kiang/" local="129703147461313640" remote="129703250400000000" />
<file name="line2.png" server="unas.com.tw/www/test/kiang/" local="129736703828285836" remote="129736712400000000" />
<file name="icon_star1.gif" server="unas.com.tw/www/test/kiang/" local="129705670664418492" remote="129705689400000000" />
<file name="icon_star2.gif" server="unas.com.tw/www/test/kiang/" local="129705670665108531" remote="129705689400000000" />
<file name="line3.png" server="unas.com.tw/www/test/kiang/" local="129723859647409963" remote="129724000800000000" />
<file name="icon_spots.png" server="unas.com.tw/www/test/kiang/" local="129812073180390600" remote="129812118600000000" />
<file name="line5.png" server="unas.com.tw/www/test/kiang/" local="129828931434092393" remote="129829002000000000" />
<file name="ui-icons_3d3d3d_256x240.png" server="unas.com.tw/www/test/kiang/" local="129756578020352147" remote="129756795600000000" />
<file name="ui-icons_d19405_256x240.png" server="unas.com.tw/www/test/kiang/" local="129756578465917632" remote="129756795600000000" />
<file name="ui-icons_454545_256x240.png" server="unas.com.tw/www/test/kiang/" local="129756577587597395" remote="129756795600000000" />
<file name="mapMarkers.png" server="unas.com.tw/www/test/kiang/" local="129742803086597593" remote="129756795600000000" />
<file name="category.png" server="unas.com.tw/www/test/kiang/" local="129828922753085868" remote="129829002000000000" />
<file name="head_s.png" server="unas.com.tw/www/test/kiang/" local="129805048839262267" remote="129805092600000000" />
<file name="head_l.png" server="unas.com.tw/www/test/kiang/" local="129805054561179542" remote="129805093200000000" />
<file name="img_sketch.png" server="unas.com.tw/www/test/kiang/" local="129829032349294413" remote="129829047000000000" />
</dwsync>